h5ad_validate/__init__.py
h5ad_validate/get_data.py
h5ad_validate/validate.py
h5ad_validate/validator.py
h5ad_validate/example/HTAN_h5ad_exemplar_2025_03_03.h5ad
h5ad_validate/reference/CL_codes_human.tsv
h5ad_validate/reference/README.md
HTAN_h5ad_validate-0.1.7.dist-info/LICENSE
HTAN_h5ad_validate-0.1.7.dist-info/METADATA
HTAN_h5ad_validate-0.1.7.dist-info/WHEEL
HTAN_h5ad_validate-0.1.7.dist-info/entry_points.txt
HTAN_h5ad_validate-0.1.7.dist-info/top_level.txt
HTAN_h5ad_validate-0.1.7.dist-info/RECORD
