Metadata-Version: 2.1
Name: HTAN-h5ad-validate
Version: 0.1.7
Summary: Validates AnnData h5ad files for adherence to HTAN sc/snRNA-seq requirements.
License: MIT License
Project-URL: Repository, https://github.com/ncihtan/h5ad
Keywords: HTAN,HTAN sc/snRNA-seq,HTAN h5ad
Requires-Python: >=3.10
License-File: LICENSE
Requires-Dist: anndata==0.10.8
Requires-Dist: array-api-compat==1.11
Requires-Dist: cellxgene-schema==5.2.3
Requires-Dist: cellxgene-ontology-guide==1.2.0
Requires-Dist: click==8.1.8
Requires-Dist: contourpy==1.3.1
Requires-Dist: cycler==0.12.1
Requires-Dist: Cython==3.0.12
Requires-Dist: fonttools==4.56.0
Requires-Dist: h5py==3.13.0
Requires-Dist: kiwisolver==1.4.8
Requires-Dist: matplotlib==3.10.1
Requires-Dist: natsort==8.4.0
Requires-Dist: numpy==1.26.4
Requires-Dist: packaging==24.2
Requires-Dist: pandas==2.2.3
Requires-Dist: pillow==11.1.0
Requires-Dist: pyparsing==3.2.1
Requires-Dist: python-dateutil==2.9.0.post0
Requires-Dist: pytz==2025.1
Requires-Dist: PyYAML==6.0.2
Requires-Dist: scipy==1.14.1
Requires-Dist: semantic-version==2.10.0
Requires-Dist: semver==3.0.4
Requires-Dist: six==1.17.0
Requires-Dist: tzdata==2025.1
Requires-Dist: xxhash==3.5.0
Provides-Extra: dev
Requires-Dist: pytest==8.3.5; extra == "dev"
